{
  "a": "###",
  "Game Ver": "Game Ver: ",
  "Start Game": "Start Game",
  "Course": "Course",
  "Setting": "Setting",
  "Exit Game": "Exit Game",
  "b": "###",
  "c": "###",
  "Game Speed":"Game Speed:",
  "Game Music Volume": "Game Music Volume:",
  "Game AI": "Game AI:",
  "Game Language": "Game Language",
  "SAVE&EXIT": "SAVE&EXIT:",
  "EXIT": "EXIT",
  "music": "music",
  "Saved": "Saved",
  "d": "###",
  "Player 1": "Player 1",
  "Player 2": "Player 2",
  "HP:": "HP:",
  "DEF:": "DEF:",
  "throw!": "throw!",
  "Return to menu": "Return to menu",
  "win this game!": "win this game!",
  "Turn": "Turn",
  "e": "###",
  "LOADING": "LOADING",
  "Please throw!": "Please throw!",
  "Kill Val is ": "Kill Val is ",
  "MISS": "MISS",
  "HP Recovery": "HP+1",
  "DEF + 1": "DEF+1",
  "cross": "cross",
  "diagonal": "diagonal",
  "tp": "tp",
  "free": "free",
  "single shot": "single shot",
  "multiple shots": "multiple shots",
  "X explosion": "X explosion",
  "bomb": "bomb",
  "life recovery": "life recovery",
  "shield": "shield",
  "f": "###",
  "Next Map": "Next Map",
  "Play": "Play",
  "Exit": "Exit",
  "default": "Default Map",
  "default 2": "Default Map 2",
  "capacity:": "player capacity:",
  "number of occ:": "number of occ:",
  "This is a default map\nAuthor:foxr lolunwer": "This is a default map\nAuthor:foxrlolunwer",
  "This is also a default map\nBut this map is bigger\nAuthor:foxr lolunwer": "This is also a default map\nBut this map is bigger\nAuthor:foxr lolunwer"
}
